
[
  {
    "Country": "India",
    "State": "Telangana",
    "Area": "Madhapur",
    "Pincode": "500081",
    "StationType": "COCO",
    "FuelType": "Petrol",
    "PumpName": "HP COCO - Madhapur Main",
    "PumpContact": "+91-40-40000001",
    "CurrentPriceUSD": 1.22,
    "PreviousPriceUSD": 1.20,
    "Lat": 17.4468,
    "Lon": 78.3866
  },
  {
    "Country": "India",
    "State": "Telangana",
    "Area": "Madhapur",
    "Pincode": "500081",
    "StationType": "CODO",
    "FuelType": "Diesel",
    "PumpName": "IOCL Pump - Kavuri Hills",
    "PumpContact": "+91-40-40000002",
    "CurrentPriceUSD": 1.06,
    "PreviousPriceUSD": 1.05,
    "Lat": 17.4419,
    "Lon": 78.4001
  },
  {
    "Country": "India",
    "State": "Telangana",
    "Area": "Madhapur",
    "Pincode": "500081",
    "StationType": "CODO",
    "FuelType": "Petrol",
      "PumpName": "BPCL - Image Gardens",
    "PumpContact": "+91-40-40000003",
    "CurrentPriceUSD": 1.21,
    "PreviousPriceUSD": 1.19,
    "Lat": 17.4473,
    "Lon": 78.3820
  },
  {
    "Country": "India",
    "State": "Telangana",
    "Area": "Madhapur",
    "Pincode": "500081",
    "StationType": "COCO",
    "FuelType": "Diesel",
    "PumpName": "Reliance - HITECH City Rd",
    "PumpContact": "+91-40-40000004",
    "CurrentPriceUSD": 1.07,
    "PreviousPriceUSD": 1.06,
    "Lat": 17.4565,
    "Lon": 78.3842
  },
  {
    "Country": "India",
    "State": "Telangana",
    "Area": "Madhapur",
    "Pincode": "500081",
    "StationType": "CODO",
    "FuelType": "Petrol",
    "PumpName": "Essar - Shamshabad Hwy (Test Far)",
    "PumpContact": "+91-40-40009999",
    "CurrentPriceUSD": 1.18,
    "PreviousPriceUSD": 1.17,
    "Lat": 17.2403,
    "Lon": 78.4294
  },
[
  /* ---------------------- SECUNDERABAD (3 stations) ---------------------- */
  {
    "Country": "India",
    "State": "Telangana",
    "Area": "Secunderabad",
    "Pincode": "500003",
    "StationType": "COCO",
    "FuelType": "Petrol",
    "PumpName": "HP Secunderabad Main",
    "PumpContact": "+91-40-40010001",
    "CurrentPriceUSD": 1.23,
    "PreviousPriceUSD": 1.21,
    "Lat": 17.4410,
    "Lon": 78.4980
  },
  {
    "Country": "India",
    "State": "Telangana",
    "Area": "Secunderabad",
    "Pincode": "500003",
    "StationType": "CODO",
    "FuelType": "Diesel",
    "PumpName": "BPCL Secunderabad Junction",
    "PumpContact": "+91-40-40010002",
    "CurrentPriceUSD": 1.09,
    "PreviousPriceUSD": 1.08,
    "Lat": 17.4383,
    "Lon": 78.5034
  },
  {
    "Country": "India",
    "State": "Telangana",
    "Area": "Secunderabad",
    "Pincode": "500003",
    "StationType": "CODO",
    "FuelType": "Petrol",
    "PumpName": "IOCL Tank Bund Road",
    "PumpContact": "+91-40-40010003",
    "CurrentPriceUSD": 1.22,
    "PreviousPriceUSD": 1.20,
    "Lat": 17.4370,
    "Lon": 78.5078
  },

  /* ---------------------- ECIL (4 stations) ---------------------- */
  {
    "Country": "India",
    "State": "Telangana",
    "Area": "ECIL",
    "Pincode": "500062",
    "StationType": "COCO",
    "FuelType": "Petrol",
    "PumpName": "HP ECIL Cross Roads",
    "PumpContact": "+91-40-40020001",
    "CurrentPriceUSD": 1.21,
    "PreviousPriceUSD": 1.19,
    "Lat": 17.4792,
    "Lon": 78.5721
  },
  {
    "Country": "India",
    "State": "Telangana",
    "Area": "ECIL",
    "Pincode": "500062",
    "StationType": "CODO",
    "FuelType": "Diesel",
    "PumpName": "BPCL ECIL Highway",
    "PumpContact": "+91-40-40020002",
    "CurrentPriceUSD": 1.07,
    "PreviousPriceUSD": 1.06,
    "Lat": 17.4785,
    "Lon": 78.5678
  },
  {
    "Country": "India",
    "State": "Telangana",
    "Area": "ECIL",
    "Pincode": "500062",
    "StationType": "COCO",
    "FuelType": "Petrol",
    "PumpName": "IOCL Moula Ali Road",
    "PumpContact": "+91-40-40020003",
    "CurrentPriceUSD": 1.22,
    "PreviousPriceUSD": 1.20,
    "Lat": 17.4721,
    "Lon": 78.5759
  },
  {
    "Country": "India",
    "State": "Telangana",
    "Area": "ECIL",
    "Pincode": "500062",
    "StationType": "CODO",
    "FuelType": "Diesel",
    "PumpName": "Essar ECIL Chowrasta",
    "PumpContact": "+91-40-40020004",
    "CurrentPriceUSD": 1.08,
    "PreviousPriceUSD": 1.07,
    "Lat": 17.4764,
    "Lon": 78.5803
  },

  /* ---------------------- HITECH CITY (4 stations) ---------------------- */
  {
    "Country": "India",
    "State": "Telangana",
    "Area": "Hitech City",
    "Pincode": "500081",
    "StationType": "COCO",
    "FuelType": "Petrol",
    "PumpName": "HP Cyber Towers Pump",
    "PumpContact": "+91-40-40030001",
    "CurrentPriceUSD": 1.24,
    "PreviousPriceUSD": 1.22,
    "Lat": 17.4485,
    "Lon": 78.3901
  },
  {
    "Country": "India",
    "State": "Telangana",
    "Area": "Hitech City",
    "Pincode": "500081",
    "StationType": "CODO",
    "FuelType": "Diesel",
    "PumpName": "BPCL Shilparamam Road",
    "PumpContact": "+91-40-40030002",
    "CurrentPriceUSD": 1.10,
    "PreviousPriceUSD": 1.09,
    "Lat": 17.4497,
    "Lon": 78.3884
  },
  {
    "Country": "India",
    "State": "Telangana",
    "Area": "Hitech City",
    "Pincode": "500081",
    "StationType": "COCO",
    "FuelType": "Petrol",
    "PumpName": "IOCL Tech Park Outlet",
    "PumpContact": "+91-40-40030003",
    "CurrentPriceUSD": 1.23,
    "PreviousPriceUSD": 1.21,
    "Lat": 17.4501,
    "Lon": 78.3923
  },
  {
    "Country": "India",
    "State": "Telangana",
    "Area": "Hitech City",
    "Pincode": "500081",
    "StationType": "CODO",
    "FuelType": "Diesel",
    "PumpName": "Reliance Hitech Square",
    "PumpContact": "+91-40-40030004",
    "CurrentPriceUSD": 1.11,
    "PreviousPriceUSD": 1.10,
    "Lat": 17.4518,
    "Lon": 78.3878
  },

  /* ---------------------- TARNAKA (5 stations) ---------------------- */
  {
    "Country": "India",
    "State": "Telangana",
    "Area": "Tarnaka",
    "Pincode": "500017",
    "StationType": "COCO",
    "FuelType": "Petrol",
    "PumpName": "HP Tarnaka Main Road",
    "PumpContact": "+91-40-40040001",
    "CurrentPriceUSD": 1.23,
    "PreviousPriceUSD": 1.21,
    "Lat": 17.4294,
    "Lon": 78.5283
  },
  {
    "Country": "India",
    "State": "Telangana",
    "Area": "Tarnaka",
    "Pincode": "500017",
    "StationType": "CODO",
    "FuelType": "Diesel",
    "PumpName": "BPCL Osmania University Gate",
    "PumpContact": "+91-40-40040002",
    "CurrentPriceUSD": 1.09,
    "PreviousPriceUSD": 1.08,
    "Lat": 17.4312,
    "Lon": 78.5342
  },
  {
    "Country": "India",
    "State": "Telangana",
    "Area": "Tarnaka",
    "Pincode": "500017",
    "StationType": "COCO",
    "FuelType": "Petrol",
    "PumpName": "IOCL Tarnaka Circle",
    "PumpContact": "+91-40-40040003",
    "CurrentPriceUSD": 1.22,
    "PreviousPriceUSD": 1.20,
    "Lat": 17.4288,
    "Lon": 78.5301
  },
  {
    "Country": "India",
    "State": "Telangana",
    "Area": "Tarnaka",
    "Pincode": "500017",
    "StationType": "CODO",
    "FuelType": "Diesel",
    "PumpName": "Essar Warasiguda Road",
    "PumpContact": "+91-40-40040004",
    "CurrentPriceUSD": 1.10,
    "PreviousPriceUSD": 1.09,
    "Lat": 17.4265,
    "Lon": 78.5360
  },
  {
    "Country": "India",
    "State": "Telangana",
    "Area": "Tarnaka",
    "Pincode": "500017",
    "StationType": "COCO",
    "FuelType": "Petrol",
    "PumpName": "Reliance New Nallakunta",
    "PumpContact": "+91-40-40040005",
    "CurrentPriceUSD": 1.24,
    "PreviousPriceUSD": 1.23,
    "Lat": 17.4251,
    "Lon": 78.5291
  },

  /* ---------------------- BEGUMPET (5 stations) ---------------------- */
  {
    "Country": "India",
    "State": "Telangana",
    "Area": "Begumpet",
    "Pincode": "500016",
    "StationType": "COCO",
    "FuelType": "Petrol",
    "PumpName": "HP Begumpet Airport Road",
    "PumpContact": "+91-40-40050001",
    "CurrentPriceUSD": 1.25,
    "PreviousPriceUSD": 1.23,
    "Lat": 17.4439,
    "Lon": 78.4676
  },
  {
    "Country": "India",
    "State": "Telangana",
    "Area": "Begumpet",
    "Pincode": "500016",
    "StationType": "CODO",
    "FuelType": "Diesel",
    "PumpName": "BPCL Begumpet Flyover",
    "PumpContact": "+91-40-40050002",
    "CurrentPriceUSD": 1.12,
    "PreviousPriceUSD": 1.11,
    "Lat": 17.4451,
    "Lon": 78.4698
  },
  {
    "Country": "India",
    "State": "Telangana",
    "Area": "Begumpet",
    "Pincode": "500016",
    "StationType": "COCO",
    "FuelType": "Petrol",
    "PumpName": "IOCL Greenlands Road",
    "PumpContact": "+91-40-40050003",
    "CurrentPriceUSD": 1.23,
    "PreviousPriceUSD": 1.22,
    "Lat": 17.4444,
    "Lon": 78.4721
  },
  {
    "Country": "India",
    "State": "Telangana",
    "Area": "Begumpet",
    "Pincode": "500016",
    "StationType": "CODO",
    "FuelType": "Diesel",
    "PumpName": "Essar SP Road",
    "PumpContact": "+91-40-40050004",
    "CurrentPriceUSD": 1.10,
    "PreviousPriceUSD": 1.09,
    "Lat": 17.4462,
    "Lon": 78.4750
  },
  {
    "Country": "India",
    "State": "Telangana",
    "Area": "Begumpet",
    "Pincode": "500016",
    "StationType": "COCO",
    "FuelType": "Petrol",
    "PumpName": "Reliance Begumpet Circle",
    "PumpContact": "+91-40-40050005",
    "CurrentPriceUSD": 1.24,
    "PreviousPriceUSD": 1.23,
    "Lat": 17.4475,
    "Lon": 78.4710
  }
]

]

